src/rtl/shared/quantizer/code/quantizer_32_16.v
module quantizer_32_16 (
    input wire clk,
    input wire rst_n,
    input wire i_valid,
    input wire signed [31:0] i_acc_raw, // Input Q6.26
    
    output reg signed [15:0] o_data,    // Output Q4.12
    output reg o_valid_out
);

    // --- Parameter Batas Q4.12 ---
    // Max: +7.999... (0x7FFF)
    // Min: -8.000... (0x8000)
    localparam signed [15:0] MAX_OUT = 16'h7FFF;
    localparam signed [15:0] MIN_OUT = 16'h8000;

    // --- Wires untuk Pengecekan Overflow ---
    // Q6.26 input range: -32 to +31.999 (6 bit integer)
    // Q4.12 output range: -8 to +7.999 (4 bit integer) 
    //
    // Kita mengambil bits [29:14] dari input, yang akan menjadi [15:0] output
    // Bits [31:30] adalah 2 MSB yang akan dibuang
    //
    // Untuk tidak overflow:
    // - Jika input positif (bit31=0): bits[31:29] harus 000 (nilai 0 sampai +7.999)
    // - Jika input negatif (bit31=1): bits[31:29] harus 111 (nilai -8.0 sampai -0.xxx)
    //
    // Jika bits[31:29] bukan 000 atau 111, berarti overflow
    
    wire [2:0] top_bits;
    assign top_bits = i_acc_raw[31:29];
    
    // Check if value in range
    wire in_range;
    assign in_range = (top_bits == 3'b000) || (top_bits == 3'b111);
    
    // Overflow flag
    wire is_overflow;
    assign is_overflow = !in_range;
    
    // Determine saturation direction based on MSB
    wire saturate_positive;
    assign saturate_positive = (i_acc_raw[31] == 1'b0);

    always @(posedge clk or negedge rst_n) begin
        if (!rst_n) begin
            o_data <= 0;
            o_valid_out <= 0;
        end else begin
            o_valid_out <= i_valid;
            
            if (i_valid) begin
                if (is_overflow) begin
                    // Saturate based on original sign
                    if (saturate_positive) begin
                        o_data <= MAX_OUT; // Positive overflow -> +MAX
                    end else begin
                        o_data <= MIN_OUT; // Negative overflow -> MIN
                    end
                end
                else begin
                    // Safe Zone: Ambil bit [29:14]
                    // Truncate 14 LSB (lose fractional precision)
                    // Keep 4 MSB integer + 12 fractional bits
                    o_data <= i_acc_raw[29:14];
                end
            end
        end
    end

endmodule

src/rtl/shared/quantizer/tb/quantizer_32_16_tb.v
`timescale 1ns/1ps

//==============================================================================
// Testbench: quantizer_32_16_tb
// Purpose: Validate quantizer_32_16 module functionality
//          Tests: normal quantization, overflow saturation, edge cases
//==============================================================================

module quantizer_32_16_tb;

    // Clock and Reset
    reg clk;
    reg rst_n;
    
    // DUT Signals
    reg i_valid;
    reg signed [31:0] i_acc_raw;
    wire signed [15:0] o_data;
    wire o_valid_out;
    
    // Test Variables
    integer test_num;
    integer pass_count;
    integer fail_count;
    reg signed [15:0] expected;
    
    //==========================================================================
    // DUT Instantiation
    //==========================================================================
    quantizer_32_16 dut (
        .clk(clk),
        .rst_n(rst_n),
        .i_valid(i_valid),
        .i_acc_raw(i_acc_raw),
        .o_data(o_data),
        .o_valid_out(o_valid_out)
    );
    
    //==========================================================================
    // Clock Generation (100 MHz)
    //==========================================================================
    initial begin
        clk = 0;
        forever #5 clk = ~clk; // 10ns period
    end
    
    //==========================================================================
    // Helper Functions
    //==========================================================================
    
    // Convert Q6.26 to float (for display)
    function real q6_26_to_float;
        input signed [31:0] val;
        begin
            q6_26_to_float = $itor(val) / (2.0 ** 26);
        end
    endfunction
    
    // Convert Q4.12 to float (for display)
    function real q4_12_to_float;
        input signed [15:0] val;
        begin
            q4_12_to_float = $itor(val) / (2.0 ** 12);
        end
    endfunction
    
    // Convert float to Q6.26
    function signed [31:0] float_to_q6_26;
        input real val;
        begin
            float_to_q6_26 = $rtoi(val * (2.0 ** 26));
        end
    endfunction
    
    // Convert float to Q4.12
    function signed [15:0] float_to_q4_12;
        input real val;
        begin
            float_to_q4_12 = $rtoi(val * (2.0 ** 12));
        end
    endfunction
    
    //==========================================================================
    // Test Procedure
    //==========================================================================
    task run_test;
        input signed [31:0] input_val;
        input signed [15:0] expected_val;
        input [80*8-1:0] test_name;
        begin
            test_num = test_num + 1;
            
            // Wait for clean clock edge
            @(negedge clk);
            
            // Apply input with setup time before posedge
            i_valid = 1'b1;
            i_acc_raw = input_val;
            expected = expected_val;
            
            // Wait for posedge to register
            @(posedge clk);
            @(negedge clk);
            i_valid = 1'b0;
            
            // Wait for output
            @(posedge clk);
            
            // Check result
            if (o_valid_out && (o_data === expected)) begin
                $display("[PASS] Test %0d: %s", test_num, test_name);
                $display("       Input:    Q6.26 = 0x%08X (%f)", input_val, q6_26_to_float(input_val));
                $display("       Output:   Q4.12 = 0x%04X (%f)", o_data, q4_12_to_float(o_data));
                $display("       Expected: Q4.12 = 0x%04X (%f)", expected, q4_12_to_float(expected));
                pass_count = pass_count + 1;
            end else begin
                $display("[FAIL] Test %0d: %s", test_num, test_name);
                $display("       Input:    Q6.26 = 0x%08X (%f) [bits31:29=%b]", input_val, q6_26_to_float(input_val), input_val[31:29]);
                $display("       Output:   Q4.12 = 0x%04X (%f)", o_data, q4_12_to_float(o_data));
                $display("       Expected: Q4.12 = 0x%04X (%f)", expected, q4_12_to_float(expected));
                $display("       o_valid_out = %b", o_valid_out);
                fail_count = fail_count + 1;
            end
            $display("");
        end
    endtask
    
    //==========================================================================
    // Main Test Sequence
    //==========================================================================
    initial begin
        // Initialize
        test_num = 0;
        pass_count = 0;
        fail_count = 0;
        
        clk = 0;
        rst_n = 0;
        i_valid = 0;
        i_acc_raw = 0;
        
        // Dump waveform
        $dumpfile("quantizer_32_16_tb.vcd");
        $dumpvars(0, quantizer_32_16_tb);
        
        $display("================================================================================");
        $display("Quantizer 32-bit to 16-bit Testbench");
        $display("Input Format:  Q6.26 (32-bit signed, range: -32 to +32)");
        $display("Output Format: Q4.12 (16-bit signed, range: -8 to +7.999)");
        $display("================================================================================");
        $display("");
        
        // Reset
        #20;
        rst_n = 1;
        #10;
        
        //======================================================================
        // Test Group 1: Normal Quantization (Within Range)
        //======================================================================
        $display("--- Test Group 1: Normal Quantization ---");
        
        // Test 1: Zero
        run_test(32'h00000000, 16'h0000, "Zero input");
        
        // Test 2: Small positive (0.5)
        run_test(float_to_q6_26(0.5), float_to_q4_12(0.5), "Small positive (0.5)");
        
        // Test 3: Small negative (-0.5)
        run_test(float_to_q6_26(-0.5), float_to_q4_12(-0.5), "Small negative (-0.5)");
        
        // Test 4: Medium positive (3.75)
        run_test(float_to_q6_26(3.75), float_to_q4_12(3.75), "Medium positive (3.75)");
        
        // Test 5: Medium negative (-3.75)
        run_test(float_to_q6_26(-3.75), float_to_q4_12(-3.75), "Medium negative (-3.75)");
        
        // Test 6: Max valid positive (~7.999)
        run_test(32'h1FFFC000, 16'h7FFF, "Max valid positive (7.999)");
        
        // Test 7: Min valid negative (~-8.000)
        run_test(32'hE0004000, 16'h8001, "Min valid negative (-7.999)");
        
        //======================================================================
        // Test Group 2: Overflow Saturation (Positive)
        //======================================================================
        $display("--- Test Group 2: Positive Overflow Saturation ---");
        
        // Test 8: Slightly over max (+8.5) -> should saturate to +7.999
        run_test(float_to_q6_26(8.5), 16'h7FFF, "Overflow +8.5 -> +7.999 (MAX)");
        
        // Test 9: Large positive (+15.0)
        run_test(float_to_q6_26(15.0), 16'h7FFF, "Overflow +15.0 -> +7.999 (MAX)");
        
        // Test 10: Very large positive (+31.0)
        run_test(float_to_q6_26(31.0), 16'h7FFF, "Overflow +31.0 -> +7.999 (MAX)");
        
        // Test 11: Edge case: bits[31:29] = 001 (overflow positive)
        run_test(32'h20000000, 16'h7FFF, "Edge case 0x20000000 -> MAX");
        
        //======================================================================
        // Test Group 3: Overflow Saturation (Negative)
        //======================================================================
        $display("--- Test Group 3: Negative Overflow Saturation ---");
        
        // Test 12: Slightly under min (-8.5) -> should saturate to -8.0
        run_test(float_to_q6_26(-8.5), 16'h8000, "Overflow -8.5 -> -8.0 (MIN)");
        
        // Test 13: Large negative (-15.0)
        run_test(float_to_q6_26(-15.0), 16'h8000, "Overflow -15.0 -> -8.0 (MIN)");
        
        // Test 14: Very large negative (-31.0)
        run_test(float_to_q6_26(-31.0), 16'h8000, "Overflow -31.0 -> -8.0 (MIN)");
        
        // Test 15: Edge case: bits[31:29] = 110 (overflow negative)
        run_test(32'hC0000000, 16'h8000, "Edge case 0xC0000000 -> MIN");
        
        //======================================================================
        // Test Group 4: Boundary Cases
        //======================================================================
        $display("--- Test Group 4: Boundary Cases ---");
        
        // Test 16: Maximum positive value that fits in Q4.12 without overflow
        // Q4.12 max = +7.999755859375 = 0x7FFF
        // In Q6.26: 0x7FFF << 14 = 0x1FFFC000, but bit[29]=1 makes it negative!
        // We need bits[31:29]=000 and bit[29]=0, so max is 0x1FFFFFFF >> 2 = 0x1FFF_BFFF
        run_test(32'h1FFFBFFF, 16'h7FFE, "Boundary: max positive inside range");
        
        // Test 17: Exactly at negative boundary
        run_test(32'hE0000000, 16'h8000, "Boundary: 0xE0000000 -> 0x8000");
        
        // Test 18: Just inside positive range
        run_test(32'h1FFF0000, 16'h7FFC, "Inside: 0x1FFF0000 -> 0x7FFC");
        
        // Test 19: Just inside negative range
        run_test(32'hE0010000, 16'h8004, "Inside: 0xE0010000 -> 0x8004");
        
        //======================================================================
        // Test Group 5: Quantization Error
        //======================================================================
        $display("--- Test Group 5: Quantization Error (LSB truncation) ---");
        
        // Test 20: Value with LSBs (should be truncated)
        run_test(32'h04001FFF, 16'h1000, "Truncation: 0x04001FFF -> 0x1000");
        
        // Test 21: Value with all LSBs set
        run_test(32'h04003FFF, 16'h1000, "Truncation: 0x04003FFF -> 0x1000");
        
        // Test 22: Value just below rounding threshold
        run_test(32'h04001000, 16'h1000, "Truncation: 0x04001000 -> 0x1000");
        
        //======================================================================
        // Test Group 6: Valid Signal Propagation
        //======================================================================
        $display("--- Test Group 6: Valid Signal Propagation ---");
        
        // Test 23: Valid signal properly propagates
        @(posedge clk);
        i_valid = 1'b1;
        i_acc_raw = float_to_q6_26(1.5);
        
        @(posedge clk);
        // At this cycle, o_valid_out should be high (registered from i_valid)
        if (o_valid_out) begin
            $display("[PASS] Test %0d: Valid signal high after 1 cycle", test_num + 1);
            pass_count = pass_count + 1;
        end else begin
            $display("[FAIL] Test %0d: Valid signal should be high after 1 cycle", test_num + 1);
            fail_count = fail_count + 1;
        end
        test_num = test_num + 1;
        
        i_valid = 1'b0;
        @(posedge clk);
        
        // Now o_valid_out should be low
        if (!o_valid_out) begin
            $display("[PASS] Test %0d: Valid signal low after input deasserted", test_num + 1);
            pass_count = pass_count + 1;
        end else begin
            $display("[FAIL] Test %0d: Valid signal should be low", test_num + 1);
            fail_count = fail_count + 1;
        end
        test_num = test_num + 1;
        $display("");
        
        //======================================================================
        // Test Summary
        //======================================================================
        #100;
        $display("================================================================================");
        $display("Test Summary:");
        $display("  Total Tests: %0d", test_num);
        $display("  Passed:      %0d", pass_count);
        $display("  Failed:      %0d", fail_count);
        
        if (fail_count == 0) begin
            $display("  Result:      ALL TESTS PASSED!");
        end else begin
            $display("  Result:      SOME TESTS FAILED");
        end
        $display("================================================================================");
        
        $finish;
    end
    
    //==========================================================================
    // Timeout Watchdog
    //==========================================================================
    initial begin
        #1000000; // 1ms timeout
        $display("ERROR: Simulation timeout!");
        $finish;
    end

endmodule

src/rtl/shared/quantizer/tb/quantizer_32_16_tb.vcd
$date
	Thu Jan 08 00:53:34 2026
$end
$version
	Icarus Verilog
$end
$timescale
	1ps
$end
$scope module quantizer_32_16_tb $end
$var wire 1 ! o_valid_out $end
$var wire 16 " o_data [15:0] $end
$var reg 1 # clk $end
$var reg 16 $ expected [15:0] $end
$var reg 32 % i_acc_raw [31:0] $end
$var reg 1 & i_valid $end
$var reg 1 ' rst_n $end
$var integer 32 ( fail_count [31:0] $end
$var integer 32 ) pass_count [31:0] $end
$var integer 32 * test_num [31:0] $end
$scope function float_to_q4_12 $end
$var real 1 + val $end
$upscope $end
$scope function float_to_q6_26 $end
$var real 1 , val $end
$upscope $end
$scope function q4_12_to_float $end
$var reg 16 - val [15:0] $end
$upscope $end
$scope function q6_26_to_float $end
$var reg 32 . val [31:0] $end
$upscope $end
$scope module dut $end
$var wire 1 # clk $end
$var wire 32 / i_acc_raw [31:0] $end
$var wire 1 & i_valid $end
$var wire 1 0 in_range $end
$var wire 1 ' rst_n $end
$var wire 1 1 saturate_positive $end
$var wire 3 2 top_bits [2:0] $end
$var wire 1 3 is_overflow $end
$var parameter 16 4 MAX_OUT $end
$var parameter 16 5 MIN_OUT $end
$var reg 16 6 o_data [15:0] $end
$var reg 1 ! o_valid_out $end
$upscope $end
$scope task run_test $end
$var reg 16 7 expected_val [15:0] $end
$var reg 32 8 input_val [31:0] $end
$var reg 640 9 test_name [639:0] $end
$upscope $end
$upscope $end
$enddefinitions $end
$comment Show the parameter values. $end
$dumpall
b1000000000000000 5
b111111111111111 4
$end
#0
$dumpvars
bx 9
bx 8
bx 7
b0 6
03
b0 2
11
10
b0 /
bx .
bx -
r0 ,
r0 +
b0 *
b0 )
b0 (
0'
0&
b0 %
bx $
0#
b0 "
0!
$end
#5000
1#
#10000
0#
#15000
1#
#20000
0#
1'
#25000
1#
#30000
b0 $
1&
0#
b1 *
b1011010011001010111001001101111001000000110100101101110011100000111010101110100 9
b0 7
b0 8
#35000
1!
1#
#40000
0&
0#
#45000
0!
b10 *
b101001101101101011000010110110001101100001000000111000001101111011100110110100101110100011010010111011001100101001000000010100000110000001011100011010100101001 9
b100000000000 7
r0.5 +
b10000000000000000000000000 8
r0.5 ,
b1 )
b0 -
b0 .
1#
#50000
b100000000000 $
b10000000000000000000000000 %
b10000000000000000000000000 /
1&
0#
#55000
b100000000000 "
b100000000000 6
1!
1#
#60000
0&
0#
#65000
0!
b11 *
b10100110110110101100001011011000110110000100000011011100110010101100111011000010111010001101001011101100110010100100000001010000010110100110000001011100011010100101001 9
b1111100000000000 7
r-0.5 +
b11111110000000000000000000000000 8
r-0.5 ,
b10 )
b100000000000 -
b10000000000000000000000000 .
1#
#70000
01
b111 2
b1111100000000000 $
b11111110000000000000000000000000 %
b11111110000000000000000000000000 /
1&
0#
#75000
b1111100000000000 "
b1111100000000000 6
1!
1#
#80000
0&
0#
#85000
0!
b100 *
b1001101011001010110010001101001011101010110110100100000011100000110111101110011011010010111010001101001011101100110010100100000001010000011001100101110001101110011010100101001 9
b11110000000000 7
r3.75 +
b1111000000000000000000000000 8
r3.75 ,
b11 )
b1111100000000000 -
b11111110000000000000000000000000 .
1#
#90000
11
b0 2
b11110000000000 $
b1111000000000000000000000000 %
b1111000000000000000000000000 /
1&
0#
#95000
b11110000000000 "
b11110000000000 6
1!
1#
#100000
0&
0#
#105000
0!
b101 *
b100110101100101011001000110100101110101011011010010000001101110011001010110011101100001011101000110100101110110011001010010000000101000001011010011001100101110001101110011010100101001 9
b1100010000000000 7
r-3.75 +
b11110001000000000000000000000000 8
r-3.75 ,
b100 )
b11110000000000 -
b1111000000000000000000000000 .
1#
#110000
01
b111 2
b1100010000000000 $
b11110001000000000000000000000000 %
b11110001000000000000000000000000 /
1&
0#
#115000
b1100010000000000 "
b1100010000000000 6
1!
1#
#120000
0&
0#
#125000
0!
b110 *
b100110101100001011110000010000001110110011000010110110001101001011001000010000001110000011011110111001101101001011101000110100101110110011001010010000000101000001101110010111000111001001110010011100100101001 9
b111111111111111 7
b11111111111111100000000000000 8
b101 )
b1100010000000000 -
b11110001000000000000000000000000 .
1#
#130000
11
b0 2
b111111111111111 $
b11111111111111100000000000000 %
b11111111111111100000000000000 /
1&
0#
#135000
b111111111111111 "
b111111111111111 6
1!
1#
#140000
0&
0#
#145000
0!
b111 *
b10011010110100101101110001000000111011001100001011011000110100101100100001000000110111001100101011001110110000101110100011010010111011001100101001000000010100000101101001101110010111000111001001110010011100100101001 9
b1000000000000001 7
b11100000000000000100000000000000 8
b110 )
b111111111111111 -
b11111111111111100000000000000 .
1#
#150000
01
b111 2
b1000000000000001 $
b11100000000000000100000000000000 %
b11100000000000000100000000000000 /
1&
0#
#155000
b1000000000000001 "
b1000000000000001 6
1!
1#
#160000
0&
0#
#165000
0!
b1000 *
b100111101110110011001010111001001100110011011000110111101110111001000000010101100111000001011100011010100100000001011010011111000100000001010110011011100101110001110010011100100111001001000000010100001001101010000010101100000101001 9
b111111111111111 7
b100010000000000000000000000000 8
r8.5 ,
b111 )
b1000000000000001 -
b11100000000000000100000000000000 .
1#
#170000
13
00
11
b1 2
b111111111111111 $
b100010000000000000000000000000 %
b100010000000000000000000000000 /
1&
0#
#175000
b111111111111111 "
b111111111111111 6
1!
1#
#180000
0&
0#
#185000
0!
b1001 *
b10011110111011001100101011100100110011001101100011011110111011100100000001010110011000100110101001011100011000000100000001011010011111000100000001010110011011100101110001110010011100100111001001000000010100001001101010000010101100000101001 9
b111100000000000000000000000000 8
r15 ,
b1000 )
b111111111111111 -
b100010000000000000000000000000 .
1#
#190000
b111100000000000000000000000000 %
b111100000000000000000000000000 /
1&
0#
#195000
1!
1#
#200000
0&
0#
#205000
0!
b1010 *
b10011110111011001100101011100100110011001101100011011110111011100100000001010110011001100110001001011100011000000100000001011010011111000100000001010110011011100101110001110010011100100111001001000000010100001001101010000010101100000101001 9
b1111100000000000000000000000000 8
r31 ,
b1001 )
b111100000000000000000000000000 .
1#
#210000
b11 2
b1111100000000000000000000000000 %
b1111100000000000000000000000000 /
1&
0#
#215000
1!
1#
#220000
0&
0#
#225000
0!
b1011 *
b10001010110010001100111011001010010000001100011011000010111001101100101001000000011000001111000001100100011000000110000001100000011000000110000001100000011000000100000001011010011111000100000010011010100000101011000 9
b100000000000000000000000000000 8
b1010 )
b1111100000000000000000000000000 .
1#
#230000
b1 2
b100000000000000000000000000000 %
b100000000000000000000000000000 /
1&
0#
#235000
1!
1#
#240000
0&
0#
#245000
0!
b1100 *
b10011110111011001100101011100100110011001101100011011110111011100100000001011010011100000101110001101010010000000101101001111100010000000101101001110000010111000110000001000000010100001001101010010010100111000101001 9
b1000000000000000 7
b11011110000000000000000000000000 8
r-8.5 ,
b1011 )
b100000000000000000000000000000 .
1#
#250000
01
b110 2
b1000000000000000 $
b11011110000000000000000000000000 %
b11011110000000000000000000000000 /
1&
0#
#255000
b1000000000000000 "
b1000000000000000 6
1!
1#
#260000
0&
0#
#265000
0!
b1101 *
b1001111011101100110010101110010011001100110110001101111011101110010000000101101001100010011010100101110001100000010000000101101001111100010000000101101001110000010111000110000001000000010100001001101010010010100111000101001 9
b11000100000000000000000000000000 8
r-15 ,
b1100 )
b1000000000000000 -
b11011110000000000000000000000000 .
1#
#270000
b11000100000000000000000000000000 %
b11000100000000000000000000000000 /
1&
0#
#275000
1!
1#
#280000
0&
0#
#285000
0!
b1110 *
b1001111011101100110010101110010011001100110110001101111011101110010000000101101001100110011000100101110001100000010000000101101001111100010000000101101001110000010111000110000001000000010100001001101010010010100111000101001 9
b10000100000000000000000000000000 8
r-31 ,
b1101 )
b11000100000000000000000000000000 .
1#
#290000
b100 2
b10000100000000000000000000000000 %
b10000100000000000000000000000000 /
1&
0#
#295000
1!
1#
#300000
0&
0#
#305000
0!
b1111 *
b10001010110010001100111011001010010000001100011011000010111001101100101001000000011000001111000010000110011000000110000001100000011000000110000001100000011000000100000001011010011111000100000010011010100100101001110 9
b11000000000000000000000000000000 8
b1110 )
b10000100000000000000000000000000 .
1#
#310000
b110 2
b11000000000000000000000000000000 %
b11000000000000000000000000000000 /
1&
0#
#315000
1!
1#
#320000
0&
0#
#325000
0!
b10000 *
b100001001101111011101010110111001100100011000010111001001111001001110100010000001101101011000010111100000100000011100000110111101110011011010010111010001101001011101100110010100100000011010010110111001110011011010010110010001100101001000000111001001100001011011100110011101100101 9
b111111111111110 7
b11111111111111011111111111111 8
b1111 )
b11000000000000000000000000000000 .
1#
#330000
03
10
11
b0 2
b111111111111110 $
b11111111111111011111111111111 %
b11111111111111011111111111111 /
1&
0#
#335000
b111111111111110 "
b111111111111110 6
1!
1#
#340000
0&
0#
#345000
0!
b10001 *
b10000100110111101110101011011100110010001100001011100100111100100111010001000000011000001111000010001010011000000110000001100000011000000110000001100000011000000100000001011010011111000100000001100000111100000111000001100000011000000110000 9
b1000000000000000 7
b11100000000000000000000000000000 8
b10000 )
b111111111111110 -
b11111111111111011111111111111 .
1#
#350000
01
b111 2
b1000000000000000 $
b11100000000000000000000000000000 %
b11100000000000000000000000000000 /
1&
0#
#355000
b1000000000000000 "
b1000000000000000 6
1!
1#
#360000
0&
0#
#365000
0!
b10010 *
b1001001011011100111001101101001011001000110010100111010001000000011000001111000001100010100011001000110010001100011000000110000001100000011000000100000001011010011111000100000001100000111100000110111010001100100011001000011 9
b111111111111100 7
b11111111111110000000000000000 8
b10001 )
b1000000000000000 -
b11100000000000000000000000000000 .
1#
#370000
11
b0 2
b111111111111100 $
b11111111111110000000000000000 %
b11111111111110000000000000000 /
1&
0#
#375000
b111111111111100 "
b111111111111100 6
1!
1#
#380000
0&
0#
#385000
0!
b10011 *
b1001001011011100111001101101001011001000110010100111010001000000011000001111000010001010011000000110000001100010011000000110000001100000011000000100000001011010011111000100000001100000111100000111000001100000011000000110100 9
b1000000000000100 7
b11100000000000010000000000000000 8
b10010 )
b111111111111100 -
b11111111111110000000000000000 .
1#
#390000
01
b111 2
b1000000000000100 $
b11100000000000010000000000000000 %
b11100000000000010000000000000000 /
1&
0#
#395000
b1000000000000100 "
b1000000000000100 6
1!
1#
#400000
0&
0#
#405000
0!
b10100 *
b101010001110010011101010110111001100011011000010111010001101001011011110110111000111010001000000011000001111000001100000011010000110000001100000011000101000110010001100100011000100000001011010011111000100000001100000111100000110001001100000011000000110000 9
b1000000000000 7
b100000000000001111111111111 8
b10011 )
b1000000000000100 -
b11100000000000010000000000000000 .
1#
#410000
11
b0 2
b1000000000000 $
b100000000000001111111111111 %
b100000000000001111111111111 /
1&
0#
#415000
b1000000000000 "
b1000000000000 6
1!
1#
#420000
0&
0#
#425000
0!
b10101 *
b101010001110010011101010110111001100011011000010111010001101001011011110110111000111010001000000011000001111000001100000011010000110000001100000011001101000110010001100100011000100000001011010011111000100000001100000111100000110001001100000011000000110000 9
b100000000000011111111111111 8
b10100 )
b1000000000000 -
b100000000000001111111111111 .
1#
#430000
b100000000000011111111111111 %
b100000000000011111111111111 /
1&
0#
#435000
1!
1#
#440000
0&
0#
#445000
0!
b10110 *
b101010001110010011101010110111001100011011000010111010001101001011011110110111000111010001000000011000001111000001100000011010000110000001100000011000100110000001100000011000000100000001011010011111000100000001100000111100000110001001100000011000000110000 9
b100000000000001000000000000 8
b10101 )
b100000000000011111111111111 .
1#
#450000
b100000000000001000000000000 %
b100000000000001000000000000 /
1&
0#
#455000
1!
1#
#460000
0&
0#
#465000
0!
b10110 )
b100000000000001000000000000 .
1#
#470000
0#
#475000
b1100000000000 "
b1100000000000 6
1!
b110000000000000000000000000 %
b110000000000000000000000000 /
r1.5 ,
1&
1#
#480000
0#
#485000
0!
0&
b10111 *
b10111 )
1#
#490000
0#
#495000
b11000 *
b11000 )
1#
