src/rtl/shared/memory/param_rom.v
//==============================================================================
// Module: param_rom
// Purpose: Static parameter ROM for HiFi-GAN layer configurations.
//          Stores layer-specific metadata (kernel size, dilation, channels, etc.)
//          Provides combinational read based on layer selection.
//
// Inputs:
//   - i_layer_sel : Layer selection index
//
// Outputs:
//   - o_kernel_size  : Kernel size for selected layer
//   - o_dilation     : Dilation factor for selected layer
//   - o_in_channels  : Number of input channels
//   - o_out_channels : Number of output channels
//
// Fixed-point Format:
//   - N/A (integer parameters only)
//
// Usage:
//   - Pre-configure parameters for each layer in the lookup table
//   - FSM reads parameters based on current layer being processed
//   - Supports up to MAX_LAYERS different layer configurations
//==============================================================================

module param_rom #(
    parameter MAX_LAYERS = 16,              // Maximum number of layers supported
    parameter PARAM_WIDTH = 8               // Bit width for each parameter
)(
    input wire [$clog2(MAX_LAYERS)-1:0]     i_layer_sel,
    
    // Layer Parameters Output
    output reg [PARAM_WIDTH-1:0]            o_kernel_size,
    output reg [PARAM_WIDTH-1:0]            o_dilation,
    output reg [PARAM_WIDTH-1:0]            o_in_channels,
    output reg [PARAM_WIDTH-1:0]            o_out_channels
);

    //==========================================================================
    // Parameter Lookup Table
    // Format: {kernel_size, dilation, in_channels, out_channels}
    //==========================================================================
    always @(*) begin
        case (i_layer_sel)
            // PostNet layers (example configuration)
            4'd0: begin
                o_kernel_size  = 8'd5;      // Kernel size = 5
                o_dilation     = 8'd1;      // Dilation = 1 (standard conv)
                o_in_channels  = 8'd1;      // Input: 1 channel (raw waveform)
                o_out_channels = 8'd32;     // Output: 32 channels
            end
            
            4'd1: begin
                o_kernel_size  = 8'd5;
                o_dilation     = 8'd1;
                o_in_channels  = 8'd32;
                o_out_channels = 8'd32;
            end
            
            4'd2: begin
                o_kernel_size  = 8'd5;
                o_dilation     = 8'd1;
                o_in_channels  = 8'd32;
                o_out_channels = 8'd32;
            end
            
            4'd3: begin
                o_kernel_size  = 8'd5;
                o_dilation     = 8'd1;
                o_in_channels  = 8'd32;
                o_out_channels = 8'd32;
            end
            
            4'd4: begin
                o_kernel_size  = 8'd5;
                o_dilation     = 8'd1;
                o_in_channels  = 8'd32;
                o_out_channels = 8'd1;      // Output: 1 channel (final waveform)
            end
            
            // Generator layers (example - customize as needed)
            4'd5: begin
                o_kernel_size  = 8'd7;
                o_dilation     = 8'd1;
                o_in_channels  = 8'd80;     // Mel spectrogram input
                o_out_channels = 8'd256;
            end
            
            4'd6: begin
                o_kernel_size  = 8'd3;
                o_dilation     = 8'd1;
                o_in_channels  = 8'd256;
                o_out_channels = 8'd128;
            end
            
            4'd7: begin
                o_kernel_size  = 8'd3;
                o_dilation     = 8'd2;      // Dilated conv
                o_in_channels  = 8'd128;
                o_out_channels = 8'd128;
            end
            
            4'd8: begin
                o_kernel_size  = 8'd3;
                o_dilation     = 8'd4;
                o_in_channels  = 8'd128;
                o_out_channels = 8'd64;
            end
            
            // Add more layers as needed...
            
            default: begin
                o_kernel_size  = 8'd3;
                o_dilation     = 8'd1;
                o_in_channels  = 8'd32;
                o_out_channels = 8'd32;
            end
        endcase
    end

endmodule

src/rtl/shared/memory/bias_mem.v
//==============================================================================
// Module: bias_mem
// Purpose: Shared bias memory for HiFi-GAN layers (Generator & PostNet).
//          Single-port synchronous read BRAM initialized from .mem file.
//          Stores 16-bit biases in simple linear addressing.
//
// Inputs:
//   - clk      : System clock
//   - rst_n    : Active-low async reset
//   - i_addr   : Read address
//   - i_rd_en  : Read enable (synchronous read)
//
// Outputs:
//   - o_data   : Bias data output (Q4.12 format, registered)
//   - o_valid  : Valid signal (registered, follows i_rd_en by 1 cycle)
//
// Fixed-point Format:
//   - Biases: Q4.12 (16-bit signed, 4 integer bits, 12 fractional bits)
//
// Memory Organization:
//   - Linear addressing: biases stored sequentially
//   - Generated from CSV using generate_memory_files.py
//   - Default depth supports full HiFi-GAN model (1,825 biases)
//   - Use hifigan_addr_map.vh for layer address constants
//==============================================================================

module bias_mem #(
    parameter DATA_WIDTH = 16,                  // Bias bit width (Q4.12)
    parameter DEPTH      = 1825,                // Memory depth (words) - full HiFiGAN
    parameter MEM_FILE   = "biases.mem",        // Initialization file
    parameter ADDR_CHECK = 0                    // Enable address range checking (debug)
)(
    input wire                          clk,
    input wire                          rst_n,
    
    // Read Interface
    input wire [$clog2(DEPTH)-1:0]      i_addr,
    input wire                          i_rd_en,
    
    // Data Output
    output reg signed [DATA_WIDTH-1:0]  o_data,
    output reg                          o_valid
);

    //==========================================================================
    // Memory Declaration (inferred BRAM)
    //==========================================================================
    reg signed [DATA_WIDTH-1:0] mem [0:DEPTH-1];
    
    //==========================================================================
    // Memory Initialization
    //==========================================================================
    initial begin
        $readmemh(MEM_FILE, mem);
    end

    //==========================================================================
    // Synchronous Read (single-cycle latency)
    //==========================================================================
    always @(posedge clk or negedge rst_n) begin
        if (!rst_n) begin
            o_data  <= {DATA_WIDTH{1'b0}};
            o_valid <= 1'b0;
        end
        else begin
            o_valid <= i_rd_en;
            
            if (i_rd_en) begin
                o_data <= mem[i_addr];
            end
        end
    end

endmodule

src/rtl/shared/memory/weight_mem.v
//==============================================================================
// Module: weight_mem
// Purpose: Shared weight memory for HiFi-GAN layers (Generator & PostNet).
//          Single-port synchronous read BRAM initialized from .mem file.
//          Stores 16-bit weights in simple linear addressing (one weight per addr).
//
// Inputs:
//   - clk      : System clock
//   - rst_n    : Active-low async reset
//   - i_addr   : Read address
//   - i_rd_en  : Read enable (synchronous read)
//
// Outputs:
//   - o_data   : Weight data output (Q2.14 format, registered)
//   - o_valid  : Valid signal (registered, follows i_rd_en by 1 cycle)
//
// Fixed-point Format:
//   - Weights: Q2.14 (16-bit signed, 2 integer bits, 14 fractional bits)
//
// Memory Organization:
//   - Linear addressing: weights stored sequentially
//   - Address calculation done by caller (FSM) or address calculator
//   - Generated from CSV using generate_memory_files.py
//   - Default depth supports full HiFi-GAN model (1,462,497 weights)
//   - Use hifigan_addr_map.vh for layer address constants
//==============================================================================

module weight_mem #(
    parameter DATA_WIDTH = 16,                  // Weight bit width (Q2.14)
    parameter DEPTH      = 1462497,             // Memory depth (words) - full HiFiGAN
    parameter MEM_FILE   = "weights.mem",       // Initialization file
    parameter ADDR_CHECK = 0                    // Enable address range checking (debug)
)(
    input wire                          clk,
    input wire                          rst_n,
    
    // Read Interface
    input wire [$clog2(DEPTH)-1:0]      i_addr,
    input wire                          i_rd_en,
    
    // Data Output
    output reg signed [DATA_WIDTH-1:0]  o_data,
    output reg                          o_valid
);

    //==========================================================================
    // Memory Declaration (inferred BRAM)
    //==========================================================================
    reg signed [DATA_WIDTH-1:0] mem [0:DEPTH-1];
    
    //==========================================================================
    // Memory Initialization
    //==========================================================================
    initial begin
        $readmemh(MEM_FILE, mem);
    end

    //==========================================================================
    // Synchronous Read (single-cycle latency)
    //==========================================================================
    always @(posedge clk or negedge rst_n) begin
        if (!rst_n) begin
            o_data  <= {DATA_WIDTH{1'b0}};
            o_valid <= 1'b0;
        end
        else begin
            o_valid <= i_rd_en;
            
            if (i_rd_en) begin
                // Address range checking (optional, for debug)
                if (ADDR_CHECK && i_addr >= DEPTH) begin
                    $display("[ERROR] weight_mem: Address out of range: %d >= %d", i_addr, DEPTH);
                    o_data <= {DATA_WIDTH{1'b0}};
                end
                else begin
                    o_data <= mem[i_addr];
                end
            end
        end
    end

endmodule

src/rtl/shared/memory/tb/memory_tb.v
//==============================================================================
// Testbench: memory_tb
// Purpose: Test shared memory modules (weight_mem, bias_mem, param_rom)
//==============================================================================

`timescale 1ns / 1ps

module memory_tb;

    //==========================================================================
    // Parameters
    //==========================================================================
    parameter DATA_WIDTH = 16;
    parameter WEIGHT_DEPTH = 256;
    parameter BIAS_DEPTH = 64;
    parameter CLK_PERIOD = 10; // 100MHz clock
    
    //==========================================================================
    // DUT Signals
    //==========================================================================
    reg clk;
    reg rst_n;
    
    // Weight memory interface
    reg [7:0] weight_addr;
    reg weight_rd_en;
    wire signed [DATA_WIDTH-1:0] weight_data;
    wire weight_valid;
    
    // Bias memory interface
    reg [5:0] bias_addr;
    reg bias_rd_en;
    wire signed [DATA_WIDTH-1:0] bias_data;
    wire bias_valid;
    
    // Param ROM interface
    reg [3:0] layer_sel;
    wire [7:0] kernel_size;
    wire [7:0] dilation;
    wire [7:0] in_channels;
    wire [7:0] out_channels;
    
    //==========================================================================
    // Clock Generation
    //==========================================================================
    initial begin
        clk = 0;
        forever #(CLK_PERIOD/2) clk = ~clk;
    end
    
    //==========================================================================
    // DUT Instantiation
    //==========================================================================
    weight_mem #(
        .DATA_WIDTH(DATA_WIDTH),
        .DEPTH(WEIGHT_DEPTH),
        .MEM_FILE("weights.mem")
    ) u_weight_mem (
        .clk     (clk),
        .rst_n   (rst_n),
        .i_addr  (weight_addr),
        .i_rd_en (weight_rd_en),
        .o_data  (weight_data),
        .o_valid (weight_valid)
    );
    
    bias_mem #(
        .DATA_WIDTH(DATA_WIDTH),
        .DEPTH(BIAS_DEPTH),
        .MEM_FILE("biases.mem")
    ) u_bias_mem (
        .clk     (clk),
        .rst_n   (rst_n),
        .i_addr  (bias_addr),
        .i_rd_en (bias_rd_en),
        .o_data  (bias_data),
        .o_valid (bias_valid)
    );
    
    param_rom #(
        .MAX_LAYERS(16),
        .PARAM_WIDTH(8)
    ) u_param_rom (
        .i_layer_sel   (layer_sel),
        .o_kernel_size (kernel_size),
        .o_dilation    (dilation),
        .o_in_channels (in_channels),
        .o_out_channels(out_channels)
    );
    
    //==========================================================================
    // Test Stimulus
    //==========================================================================
    initial begin
        // Initialize signals
        rst_n = 0;
        weight_addr = 0;
        weight_rd_en = 0;
        bias_addr = 0;
        bias_rd_en = 0;
        layer_sel = 0;
        
        // Wait for reset
        #(CLK_PERIOD * 5);
        rst_n = 1;
        #(CLK_PERIOD * 2);
        
        $display("===== Memory Module Testbench =====");
        $display("Time: %0t ns", $time);
        
        //----------------------------------------------------------------------
        // Test 1: Weight Memory Sequential Read
        //----------------------------------------------------------------------
        $display("\n[Test 1] Weight Memory Sequential Read");
        repeat (10) begin
            @(posedge clk);
            weight_rd_en = 1;
            @(posedge clk);
            weight_rd_en = 0;
            
            @(posedge clk);
            if (weight_valid) begin
                $display("  Addr: 0x%02X -> Data: 0x%04X (Q2.14: %f)", 
                         weight_addr, weight_data, 
                         $signed(weight_data) / 16384.0);
            end
            
            weight_addr = weight_addr + 1;
        end
        
        //----------------------------------------------------------------------
        // Test 2: Bias Memory Sequential Read
        //----------------------------------------------------------------------
        $display("\n[Test 2] Bias Memory Sequential Read");
        repeat (10) begin
            @(posedge clk);
            bias_rd_en = 1;
            @(posedge clk);
            bias_rd_en = 0;
            
            @(posedge clk);
            if (bias_valid) begin
                $display("  Addr: 0x%02X -> Data: 0x%04X (Q4.12: %f)", 
                         bias_addr, bias_data,
                         $signed(bias_data) / 4096.0);
            end
            
            bias_addr = bias_addr + 1;
        end
        
        //----------------------------------------------------------------------
        // Test 3: Param ROM Read (combinational)
        //----------------------------------------------------------------------
        $display("\n[Test 3] Param ROM Layer Configuration");
        for (layer_sel = 0; layer_sel < 10; layer_sel = layer_sel + 1) begin
            @(posedge clk);
            #1; // Small delay for combinational propagation
            $display("  Layer %0d: K=%0d, D=%0d, InCh=%0d, OutCh=%0d",
                     layer_sel, kernel_size, dilation, in_channels, out_channels);
        end
        
        //----------------------------------------------------------------------
        // Test 4: Random Access Pattern
        //----------------------------------------------------------------------
        $display("\n[Test 4] Random Weight Access");
        weight_addr = 8'h0A;
        @(posedge clk);
        weight_rd_en = 1;
        @(posedge clk);
        weight_rd_en = 0;
        @(posedge clk);
        if (weight_valid)
            $display("  Random Addr: 0x%02X -> Data: 0x%04X", weight_addr, weight_data);
        
        weight_addr = 8'h2F;
        @(posedge clk);
        weight_rd_en = 1;
        @(posedge clk);
        weight_rd_en = 0;
        @(posedge clk);
        if (weight_valid)
            $display("  Random Addr: 0x%02X -> Data: 0x%04X", weight_addr, weight_data);
        
        //----------------------------------------------------------------------
        // Test Complete
        //----------------------------------------------------------------------
        #(CLK_PERIOD * 10);
        $display("\n===== Test Complete =====");
        $display("All memory modules functional.");
        $finish;
    end
    
    //==========================================================================
    // Waveform Dump (for GTKWave or Vivado Simulator)
    //==========================================================================
    initial begin
        $dumpfile("memory_tb.vcd");
        $dumpvars(0, memory_tb);
    end

endmodule

src/rtl/shared/memory/tb/memory_tb.vcd
$date
	Wed Jan 14 01:21:23 2026
$end
$version
	Icarus Verilog
$end
$timescale
	1ps
$end
$scope module memory_tb $end
$var wire 1 ! weight_valid $end
$var wire 16 " weight_data [15:0] $end
$var wire 8 # out_channels [7:0] $end
$var wire 8 $ kernel_size [7:0] $end
$var wire 8 % in_channels [7:0] $end
$var wire 8 & dilation [7:0] $end
$var wire 1 ' bias_valid $end
$var wire 16 ( bias_data [15:0] $end
$var parameter 32 ) BIAS_DEPTH $end
$var parameter 32 * CLK_PERIOD $end
$var parameter 32 + DATA_WIDTH $end
$var parameter 32 , WEIGHT_DEPTH $end
$var reg 6 - bias_addr [5:0] $end
$var reg 1 . bias_rd_en $end
$var reg 1 / clk $end
$var reg 4 0 layer_sel [3:0] $end
$var reg 1 1 rst_n $end
$var reg 8 2 weight_addr [7:0] $end
$var reg 1 3 weight_rd_en $end
$scope module u_bias_mem $end
$var wire 1 / clk $end
$var wire 6 4 i_addr [5:0] $end
$var wire 1 . i_rd_en $end
$var wire 1 1 rst_n $end
$var parameter 32 5 ADDR_CHECK $end
$var parameter 32 6 DATA_WIDTH $end
$var parameter 32 7 DEPTH $end
$var parameter 80 8 MEM_FILE $end
$var reg 16 9 o_data [15:0] $end
$var reg 1 ' o_valid $end
$upscope $end
$scope module u_param_rom $end
$var wire 4 : i_layer_sel [3:0] $end
$var parameter 32 ; MAX_LAYERS $end
$var parameter 32 < PARAM_WIDTH $end
$var reg 8 = o_dilation [7:0] $end
$var reg 8 > o_in_channels [7:0] $end
$var reg 8 ? o_kernel_size [7:0] $end
$var reg 8 @ o_out_channels [7:0] $end
$upscope $end
$scope module u_weight_mem $end
$var wire 1 / clk $end
$var wire 8 A i_addr [7:0] $end
$var wire 1 3 i_rd_en $end
$var wire 1 1 rst_n $end
$var parameter 32 B ADDR_CHECK $end
$var parameter 32 C DATA_WIDTH $end
$var parameter 32 D DEPTH $end
$var parameter 88 E MEM_FILE $end
$var reg 16 F o_data [15:0] $end
$var reg 1 ! o_valid $end
$upscope $end
$upscope $end
$enddefinitions $end
$comment Show the parameter values. $end
$dumpall
b111011101100101011010010110011101101000011101000111001100101110011011010110010101101101 E
b100000000 D
b10000 C
b0 B
b1000 <
b10000 ;
b1100010011010010110000101110011011001010111001100101110011011010110010101101101 8
b1000000 7
b10000 6
b0 5
b100000000 ,
b10000 +
b1010 *
b1000000 )
$end
#0
$dumpvars
b0 F
b0 A
b100000 @
b101 ?
b1 >
b1 =
b0 :
b0 9
b0 4
03
b0 2
01
b0 0
0/
0.
b0 -
b0 (
0'
b1 &
b1 %
b101 $
b100000 #
b0 "
0!
$end
#5000
1/
#10000
0/
#15000
1/
#20000
0/
#25000
1/
#30000
0/
#35000
1/
#40000
0/
#45000
1/
#50000
0/
11
#55000
1/
#60000
0/
#65000
1/
#70000
0/
#75000
bx "
bx F
1!
13
1/
#80000
0/
#85000
0!
03
1/
#90000
0/
#95000
b1 2
b1 A
1/
#100000
0/
#105000
1!
13
1/
#110000
0/
#115000
0!
03
1/
#120000
0/
#125000
b10 2
b10 A
1/
#130000
0/
#135000
1!
13
1/
#140000
0/
#145000
0!
03
1/
#150000
0/
#155000
b11 2
b11 A
1/
#160000
0/
#165000
1!
13
1/
#170000
0/
#175000
0!
03
1/
#180000
0/
#185000
b100 2
b100 A
1/
#190000
0/
#195000
1!
13
1/
#200000
0/
#205000
0!
03
1/
#210000
0/
#215000
b101 2
b101 A
1/
#220000
0/
#225000
1!
13
1/
#230000
0/
#235000
0!
03
1/
#240000
0/
#245000
b110 2
b110 A
1/
#250000
0/
#255000
1!
13
1/
#260000
0/
#265000
0!
03
1/
#270000
0/
#275000
b111 2
b111 A
1/
#280000
0/
#285000
1!
13
1/
#290000
0/
#295000
0!
03
1/
#300000
0/
#305000
b1000 2
b1000 A
1/
#310000
0/
#315000
1!
13
1/
#320000
0/
#325000
0!
03
1/
#330000
0/
#335000
b1001 2
b1001 A
1/
#340000
0/
#345000
1!
13
1/
#350000
0/
#355000
0!
03
1/
#360000
0/
#365000
b1010 2
b1010 A
1/
#370000
0/
#375000
bx (
bx 9
1'
1.
1/
#380000
0/
#385000
0'
0.
1/
#390000
0/
#395000
b1 -
b1 4
1/
#400000
0/
#405000
1'
1.
1/
#410000
0/
#415000
0'
0.
1/
#420000
0/
#425000
b10 -
b10 4
1/
#430000
0/
#435000
1'
1.
1/
#440000
0/
#445000
0'
0.
1/
#450000
0/
#455000
b11 -
b11 4
1/
#460000
0/
#465000
1'
1.
1/
#470000
0/
#475000
0'
0.
1/
#480000
0/
#485000
b100 -
b100 4
1/
#490000
0/
#495000
1'
1.
1/
#500000
0/
#505000
0'
0.
1/
#510000
0/
#515000
b101 -
b101 4
1/
#520000
0/
#525000
1'
1.
1/
#530000
0/
#535000
0'
0.
1/
#540000
0/
#545000
b110 -
b110 4
1/
#550000
0/
#555000
1'
1.
1/
#560000
0/
#565000
0'
0.
1/
#570000
0/
#575000
b111 -
b111 4
1/
#580000
0/
#585000
1'
1.
1/
#590000
0/
#595000
0'
0.
1/
#600000
0/
#605000
b1000 -
b1000 4
1/
#610000
0/
#615000
1'
1.
1/
#620000
0/
#625000
0'
0.
1/
#630000
0/
#635000
b1001 -
b1001 4
1/
#640000
0/
#645000
1'
1.
1/
#650000
0/
#655000
0'
0.
1/
#660000
0/
#665000
b1010 -
b1010 4
1/
#670000
0/
#675000
1/
#676000
b100000 %
b100000 >
b1 0
b1 :
#680000
0/
#685000
1/
#686000
b10 0
b10 :
#690000
0/
#695000
1/
#696000
b11 0
b11 :
#700000
0/
#705000
1/
#706000
b1 #
b1 @
b100 0
b100 :
#710000
0/
#715000
1/
#716000
b0 #
b0 @
b1010000 %
b1010000 >
b111 $
b111 ?
b101 0
b101 :
#720000
0/
#725000
1/
#726000
b10000000 #
b10000000 @
b0 %
b0 >
b11 $
b11 ?
b110 0
b110 :
#730000
0/
#735000
1/
#736000
b10000000 %
b10000000 >
b10 &
b10 =
b111 0
b111 :
#740000
0/
#745000
1/
#746000
b1000000 #
b1000000 @
b100 &
b100 =
b1000 0
b1000 :
#750000
0/
#755000
1/
#756000
b100000 #
b100000 @
b100000 %
b100000 >
b1 &
b1 =
b1001 0
b1001 :
#760000
0/
#765000
1/
#766000
b1010 0
b1010 :
#770000
0/
#775000
1!
13
1/
#780000
0/
#785000
0!
03
1/
#790000
0/
#795000
b101111 2
b101111 A
1/
#800000
0/
#805000
1!
13
1/
#810000
0/
#815000
0!
03
1/
