src/rtl/generator/mrf_block/combined_tb_mrf_block.v
`timescale 1ns / 1ps

//=============================================================================
// AUTO-GENERATED COMBINED FILE
// Menggabungkan: mrf_block.v + tb_mrf_block.v
// Satu file siap untuk simulasi tanpa perlu `include
//=============================================================================

//=============================================================================
// ====================== RESIDUAL BLOCK MODULE ==============================
//=============================================================================

module residual_block #(
    parameter DWIDTH = 16,
    parameter KERNEL_SIZE = 3
)(
    input  wire                clk,
    input  wire                rst_n,
    input  wire                start,
    input  wire signed [DWIDTH-1:0] din,
    
    output reg                 done,
    output reg  signed [DWIDTH-1:0] dout
);
    
    always @(posedge clk or negedge rst_n) begin
        if (!rst_n) begin
            dout <= 0;
            done <= 0;
        end else begin
            if (start) begin
                done <= 0;
                dout <= din; // Pass-through (simplified for simulation)
                repeat(2) @(posedge clk); // Simulate processing latency
                done <= 1;
            end else begin
                done <= 0;
            end
        end
    end
    
endmodule

//=============================================================================
// ====================== MRF BLOCK MODULE ===================================
//=============================================================================

module mrf_block #(
    parameter DWIDTH = 16,          // Data width (fixed-point)
    parameter K1 = 3,               // Kernel size for Branch 1
    parameter K2 = 7,               // Kernel size for Branch 2
    parameter K3 = 11,              // Kernel size for Branch 3
    parameter Q_SCALE = 0           // Placeholder for Q-format scaling if needed
)(
    input  wire                clk,
    input  wire                rst_n,
    input  wire                start,      // Handshake: Start trigger
    input  wire signed [DWIDTH-1:0] din,   // Input data (from Upsample)
    
    output reg                 done,       // Handshake: Done signal
    output reg  signed [DWIDTH-1:0] dout   // Output data (Sum of all branches)
);

    //-------------------------------------------------------------------------
    // 1. Internal Signals
    //-------------------------------------------------------------------------
    wire signed [DWIDTH-1:0] branch1_out;
    wire signed [DWIDTH-1:0] branch2_out;
    wire signed [DWIDTH-1:0] branch3_out;

    wire branch1_done;
    wire branch2_done;
    wire branch3_done;

    // Temporary sum with extra bits to handle overflow before saturation
    wire signed [DWIDTH+1:0] temp_sum;

    //-------------------------------------------------------------------------
    // 2. Instantiate Residual Blocks (Branches)
    //-------------------------------------------------------------------------
    
    // Branch 1: Kernel Size K1
    residual_block #(
        .DWIDTH(DWIDTH),
        .KERNEL_SIZE(K1)
    ) u_res_block_1 (
        .clk    (clk),
        .rst_n  (rst_n),
        .start  (start),
        .din    (din),
        .done   (branch1_done),
        .dout   (branch1_out)
    );

    // Branch 2: Kernel Size K2
    residual_block #(
        .DWIDTH(DWIDTH),
        .KERNEL_SIZE(K2)
    ) u_res_block_2 (
        .clk    (clk),
        .rst_n  (rst_n),
        .start  (start),
        .din    (din),
        .done   (branch2_done),
        .dout   (branch2_out)
    );

    // Branch 3: Kernel Size K3
    residual_block #(
        .DWIDTH(DWIDTH),
        .KERNEL_SIZE(K3)
    ) u_res_block_3 (
        .clk    (clk),
        .rst_n  (rst_n),
        .start  (start),
        .din    (din),
        .done   (branch3_done),
        .dout   (branch3_out)
    );

    //-------------------------------------------------------------------------
    // 3. Summation and Saturation Logic
    //-------------------------------------------------------------------------
    
    // Add all branches: A + B + C
    assign temp_sum = branch1_out + branch2_out + branch3_out;

    // Constants for saturation (Max positive and Min negative values)
    localparam signed [DWIDTH-1:0] MAX_VAL = {1'b0, {(DWIDTH-1){1'b1}}}; // e.g., 011...1
    localparam signed [DWIDTH-1:0] MIN_VAL = {1'b1, {(DWIDTH-1){1'b0}}}; // e.g., 100...0

    always @(posedge clk or negedge rst_n) begin
        if (!rst_n) begin
            dout <= 0;
            done <= 0;
        end else begin
            // Wait for all branches to complete
            if (branch1_done && branch2_done && branch3_done) begin
                done <= 1'b1;
                
                // SATURATION LOGIC
                if (temp_sum > MAX_VAL) begin
                    dout <= MAX_VAL;
                end else if (temp_sum < MIN_VAL) begin
                    dout <= MIN_VAL;
                end else begin
                    dout <= temp_sum[DWIDTH-1:0];
                end
            end else begin
                done <= 1'b0;
            end
        end
    end

endmodule

//=============================================================================
// ====================== TESTBENCH MODULE ===================================
//=============================================================================

module tb_mrf_block();
    parameter DWIDTH = 16;
    
    reg clk;
    reg rst_n;
    reg start;
    reg signed [DWIDTH-1:0] din;
    
    wire done;
    wire signed [DWIDTH-1:0] dout;

    //-------------------------------------------------------------------------
    // Instantiate Unit Under Test (UUT)
    //-------------------------------------------------------------------------
    mrf_block #(
        .DWIDTH(DWIDTH),
        .K1(3),
        .K2(7),
        .K3(11)
    ) uut (
        .clk    (clk),
        .rst_n  (rst_n),
        .start  (start),
        .din    (din),
        .done   (done),
        .dout   (dout)
    );

    //-------------------------------------------------------------------------
    // Clock Generation
    //-------------------------------------------------------------------------
    always #5 clk = ~clk; // 100MHz

    //-------------------------------------------------------------------------
    // Test Scenario
    //-------------------------------------------------------------------------
    initial begin
        $dumpfile("tb_mrf_block.vcd");
        $dumpvars(0, tb_mrf_block);
        
        // Initialize
        clk = 0;
        rst_n = 0;
        start = 0;
        din = 0;

        // Reset
        #20 rst_n = 1;
        #20;

        // TEST CASE 1: Basic Flow with input 1000
        $display("--- Starting Test Case 1: MRF Block Pipeline ---");
        $display("Input: 1000");
        
        din = 16'd1000;
        start = 1;
        #10 start = 0; // Pulse start

        // Wait for completion
        wait(done);
        
        #10;
        $display("Output: %d (Expected: 3000 - sum of 3 branches)", dout);
        
        if (dout == 16'd3000) begin
            $display("PASS: Correct summation of all branches");
        end else begin
            $display("INFO: Output is %d (Note: Simplified residual blocks may affect result)", dout);
        end

        #50;
        
        // TEST CASE 2: Different value
        $display("\n--- Starting Test Case 2: Different Value ---");
        $display("Input: 500");
        
        din = 16'd500;
        start = 1;
        #10 start = 0;
        
        wait(done);
        #10;
        $display("Output: %d", dout);

        #50;
        $finish;
    end

endmodule

src/rtl/generator/mrf_block/tb_mrf_block.vcd
$date
	Tue Jan 13 10:21:24 2026
$end
$version
	Icarus Verilog
$end
$timescale
	1ps
$end
$scope module tb_mrf_block $end
$var wire 16 ! dout [15:0] $end
$var wire 1 " done $end
$var parameter 32 # DWIDTH $end
$var reg 1 $ clk $end
$var reg 16 % din [15:0] $end
$var reg 1 & rst_n $end
$var reg 1 ' start $end
$scope module uut $end
$var wire 1 $ clk $end
$var wire 16 ( din [15:0] $end
$var wire 1 & rst_n $end
$var wire 1 ' start $end
$var wire 18 ) temp_sum [17:0] $end
$var wire 16 * branch3_out [15:0] $end
$var wire 1 + branch3_done $end
$var wire 16 , branch2_out [15:0] $end
$var wire 1 - branch2_done $end
$var wire 16 . branch1_out [15:0] $end
$var wire 1 / branch1_done $end
$var parameter 32 0 DWIDTH $end
$var parameter 32 1 K1 $end
$var parameter 32 2 K2 $end
$var parameter 32 3 K3 $end
$var parameter 16 4 MAX_VAL $end
$var parameter 16 5 MIN_VAL $end
$var parameter 32 6 Q_SCALE $end
$var reg 1 " done $end
$var reg 16 7 dout [15:0] $end
$scope module u_res_block_1 $end
$var wire 1 $ clk $end
$var wire 16 8 din [15:0] $end
$var wire 1 & rst_n $end
$var wire 1 ' start $end
$var parameter 32 9 DWIDTH $end
$var parameter 32 : KERNEL_SIZE $end
$var reg 1 / done $end
$var reg 16 ; dout [15:0] $end
$upscope $end
$scope module u_res_block_2 $end
$var wire 1 $ clk $end
$var wire 16 < din [15:0] $end
$var wire 1 & rst_n $end
$var wire 1 ' start $end
$var parameter 32 = DWIDTH $end
$var parameter 32 > KERNEL_SIZE $end
$var reg 1 - done $end
$var reg 16 ? dout [15:0] $end
$upscope $end
$scope module u_res_block_3 $end
$var wire 1 $ clk $end
$var wire 16 @ din [15:0] $end
$var wire 1 & rst_n $end
$var wire 1 ' start $end
$var parameter 32 A DWIDTH $end
$var parameter 32 B KERNEL_SIZE $end
$var reg 1 + done $end
$var reg 16 C dout [15:0] $end
$upscope $end
$upscope $end
$upscope $end
$enddefinitions $end
$comment Show the parameter values. $end
$dumpall
b1011 B
b10000 A
b111 >
b10000 =
b11 :
b10000 9
b0 6
b1000000000000000 5
b111111111111111 4
b1011 3
b111 2
b11 1
b10000 0
b10000 #
$end
#0
$dumpvars
b0 C
b0 @
b0 ?
b0 <
b0 ;
b0 8
b0 7
0/
b0 .
0-
b0 ,
0+
b0 *
b0 )
b0 (
0'
0&
b0 %
0$
0"
b0 !
$end
#5000
1$
#10000
0$
#15000
1$
#20000
0$
1&
#25000
1$
#30000
0$
#35000
1$
#40000
0$
1'
b1111101000 %
b1111101000 (
b1111101000 8
b1111101000 <
b1111101000 @
#45000
b1111101000 *
b1111101000 C
b1111101000 ,
b1111101000 ?
b101110111000 )
b1111101000 .
b1111101000 ;
1$
#50000
0$
0'
#55000
1$
#60000
0$
#65000
1+
1-
1/
1$
#70000
0$
#75000
0/
0-
0+
b101110111000 !
b101110111000 7
1"
1$
#80000
0$
#85000
0"
1$
#90000
0$
#95000
1$
#100000
0$
#105000
1$
#110000
0$
#115000
1$
#120000
0$
#125000
1$
#130000
0$
#135000
b111110100 .
b111110100 ;
b111110100 ,
b111110100 ?
b10111011100 )
b111110100 *
b111110100 C
1$
1'
b111110100 %
b111110100 (
b111110100 8
b111110100 <
b111110100 @
#140000
0$
#145000
1$
0'
#150000
0$
#155000
1/
1-
1+
1$
#160000
0$
#165000
0+
0-
0/
b10111011100 !
b10111011100 7
1"
1$
#170000
0$
#175000
0"
1$
