src/rtl/shared/activation_unit/code/leaky_relu_q15.v
// Leaky ReLU - Q1.15
// y = x            , x >= 0
// y = x / 8 (shift), x <  0

module leaky_relu_q15 (
    input  wire signed [15:0] x,
    output reg  signed [15:0] y
);
    always @* begin
        if (x >= 0)
            y = x;
        else
            y = x >>> 3;   // divide by 8
    end
endmodule

src/rtl/shared/activation_unit/tb/tb_leaky_relu.v
`timescale 1ns/1ps

module tb_leaky_relu;

    reg  signed [15:0] x;
    wire signed [15:0] y;

    leaky_relu_q15 dut (
        .x(x),
        .y(y)
    );

    initial begin
        $dumpfile("leaky_relu.vcd");
        $dumpvars(0, tb_leaky_relu);

        $display("Testing Leaky ReLU");
        $display("   x (dec)    ->    y (dec)     Expected");

        // Test zero
        x = 16'sh0000;  #10;  $display("%d -> %d     (0)", x, y);

        // Test positive values (should pass through)
        x = 16'sh1000;  #10;  $display("%d -> %d     (4096)", x, y);
        x = 16'sh2000;  #10;  $display("%d -> %d     (8192)", x, y);
        x = 16'sh4000;  #10;  $display("%d -> %d     (16384)", x, y);
        x = 16'sh7FFF;  #10;  $display("%d -> %d     (32767)", x, y);

        // Test negative values (should be divided by 8)
        x = -16'sh0800; #10;  $display("%d -> %d     (-256)", x, y);   // -2048 / 8 = -256
        x = -16'sh1000; #10;  $display("%d -> %d     (-512)", x, y);   // -4096 / 8 = -512
        x = -16'sh2000; #10;  $display("%d -> %d     (-1024)", x, y);  // -8192 / 8 = -1024
        x = -16'sh4000; #10;  $display("%d -> %d     (-2048)", x, y);  // -16384 / 8 = -2048
        x = -16'sh7FFF; #10;  $display("%d -> %d     (-4096)", x, y);  // -32767 / 8 = -4095.875 ≈ -4096

        $finish;
    end

endmodule

src/rtl/shared/activation_unit/leaky_relu.vcd
$date
	Tue Jan 13 23:56:36 2026
$end
$version
	Icarus Verilog
$end
$timescale
	1ps
$end
$scope module tb_leaky_relu $end
$var wire 16 ! y [15:0] $end
$var reg 16 " x [15:0] $end
$scope module dut $end
$var wire 16 # x [15:0] $end
$var reg 16 $ y [15:0] $end
$upscope $end
$upscope $end
$enddefinitions $end
$comment Show the parameter values. $end
$dumpall
$end
#0
$dumpvars
b0 $
b0 #
b0 "
b0 !
$end
#10000
b1000000000000 !
b1000000000000 $
b1000000000000 "
b1000000000000 #
#20000
b10000000000000 !
b10000000000000 $
b10000000000000 "
b10000000000000 #
#30000
b100000000000000 !
b100000000000000 $
b100000000000000 "
b100000000000000 #
#40000
b111111111111111 !
b111111111111111 $
b111111111111111 "
b111111111111111 #
#50000
b1111111100000000 !
b1111111100000000 $
b1111100000000000 "
b1111100000000000 #
#60000
b1111111000000000 !
b1111111000000000 $
b1111000000000000 "
b1111000000000000 #
#70000
b1111110000000000 !
b1111110000000000 $
b1110000000000000 "
b1110000000000000 #
#80000
b1111100000000000 !
b1111100000000000 $
b1100000000000000 "
b1100000000000000 #
#90000
b1111000000000000 !
b1111000000000000 $
b1000000000000001 "
b1000000000000001 #
