src/rtl/shared/activation_unit/code/tanh_approx_q15.v
// Tanh Approx - Q1.15
// Very light piecewise approx:
// small |x| -> linear
// medium -> ~0.8
// large  -> ~0.99

module tanh_approx_q15 (
    input  wire signed [15:0] x,
    output reg  signed [15:0] y
);

    localparam signed [15:0] TH_MID  = 16'sh4000; // 0.5
    localparam signed [15:0] TH_HIGH = 16'sh7333; // ~0.9
    localparam signed [15:0] Y_MID   = 16'sh6666; // ~0.8
    localparam signed [15:0] Y_HIGH  = 16'sh7EC8; // ~0.99

    wire signed [15:0] a = (x[15]) ? -x : x; // abs

    always @* begin
        if (a >= TH_HIGH)
            y = x[15] ? -Y_HIGH : Y_HIGH;
        else if (a >= TH_MID)
            y = x[15] ? -Y_MID  : Y_MID;
        else
            y = x;
    end
endmodule

src/rtl/shared/activation_unit/tb/tb_tanh.v
`timescale 1ns/1ps

module tb_tanh;

    reg  signed [15:0] x;
    wire signed [15:0] y;

    tanh_approx_q15 dut (
        .x(x),
        .y(y)
    );

    initial begin
        $dumpfile("tanh.vcd");
        $dumpvars(0, tb_tanh);

        $display("Testing Tanh Approx");
        $display("   x (dec)    ->    y (dec)");

        x = 16'sh0000;  #10;  $display("%d -> %d", x, y);   // 0
        x = 16'sh2000;  #10;  $display("%d -> %d", x, y);   // +0.25
        x = 16'sh4000;  #10;  $display("%d -> %d", x, y);   // +0.5
        x = 16'sh6000;  #10;  $display("%d -> %d", x, y);   // +0.75
        x = 16'sh7FFF;  #10;  $display("%d -> %d", x, y);   // ~1

        x = -16'sh2000; #10;  $display("%d -> %d", x, y);
        x = -16'sh4000; #10;  $display("%d -> %d", x, y);
        x = -16'sh7FFF; #10;  $display("%d -> %d", x, y);

        $finish;
    end

endmodule

src/rtl/shared/activation_unit/tanh.vcd
$date
	Tue Jan 13 23:36:07 2026
$end
$version
	Icarus Verilog
$end
$timescale
	1ps
$end
$scope module tb_tanh $end
$var wire 16 ! y [15:0] $end
$var reg 16 " x [15:0] $end
$scope module dut $end
$var wire 16 # x [15:0] $end
$var wire 16 $ a [15:0] $end
$var parameter 16 % TH_HIGH $end
$var parameter 16 & TH_MID $end
$var parameter 16 ' Y_HIGH $end
$var parameter 16 ( Y_MID $end
$var reg 16 ) y [15:0] $end
$upscope $end
$upscope $end
$enddefinitions $end
$comment Show the parameter values. $end
$dumpall
b110011001100110 (
b111111011001000 '
b100000000000000 &
b111001100110011 %
$end
#0
$dumpvars
b0 )
b0 $
b0 #
b0 "
b0 !
$end
#10000
b10000000000000 !
b10000000000000 )
b10000000000000 $
b10000000000000 "
b10000000000000 #
#20000
b110011001100110 !
b110011001100110 )
b100000000000000 $
b100000000000000 "
b100000000000000 #
#30000
b110000000000000 $
b110000000000000 "
b110000000000000 #
#40000
b111111011001000 !
b111111011001000 )
b111111111111111 $
b111111111111111 "
b111111111111111 #
#50000
b1110000000000000 !
b1110000000000000 )
b10000000000000 $
b1110000000000000 "
b1110000000000000 #
#60000
b1001100110011010 !
b1001100110011010 )
b100000000000000 $
b1100000000000000 "
b1100000000000000 #
#70000
b1000000100111000 !
b1000000100111000 )
b111111111111111 $
b1000000000000001 "
b1000000000000001 #
